setup.py
src/infi/__init__.py
src/infi/__version__.py
src/infi.mountoolinux.egg-info/PKG-INFO
src/infi.mountoolinux.egg-info/SOURCES.txt
src/infi.mountoolinux.egg-info/dependency_links.txt
src/infi.mountoolinux.egg-info/entry_points.txt
src/infi.mountoolinux.egg-info/namespace_packages.txt
src/infi.mountoolinux.egg-info/not-zip-safe
src/infi.mountoolinux.egg-info/requires.txt
src/infi.mountoolinux.egg-info/top_level.txt
src/infi/mountoolinux/__init__.py
src/infi/mountoolinux/__version__.py
src/infi/mountoolinux/mount/__init__.py
src/infi/mountoolinux/mount/errors/__init__.py
src/infi/mountoolinux/mount/manager/__init__.py
src/infi/mountoolinux/mount/manager/mounter/__init__.py
src/infi/mountoolinux/mount/manager/mounter/tests/__init__.py
src/infi/mountoolinux/mount/manager/show_mounts/__init__.py
src/infi/mountoolinux/mount/manager/show_mounts/tests/__init__.py
src/infi/mountoolinux/mount/manager/supported_file_systems/__init__.py
src/infi/mountoolinux/mount/manager/supported_file_systems/tests/__init__.py
src/infi/mountoolinux/mount/manager/tests/__init__.py