Metadata-Version: 1.1
Name: infi.mountoolinux
Version: 0.1.16
Summary: Python library for handling POSIX mounts
Home-page: https://github.com/Infinidat/infi.mountoolinux
Author: Guy Rozendorn
Author-email: guy@rzn.co.il
License: PSF
Platform: UNKNOWN
Classifier: Intended Audience :: Developers
Classifier: Intended Audience :: System Administrators
Classifier: License :: OSI Approved :: Python Software Foundation License
Classifier: Operating System :: OS Independent
Classifier: Programming Language :: Python
Classifier: Topic :: Software Development :: Libraries :: Python Modules
